processy/__init__.py
processy-1.0.7.dist-info/DESCRIPTION.rst
processy-1.0.7.dist-info/METADATA
processy-1.0.7.dist-info/RECORD
processy-1.0.7.dist-info/WHEEL
processy-1.0.7.dist-info/entry_points.txt
processy-1.0.7.dist-info/metadata.json
processy-1.0.7.dist-info/top_level.txt
