Metadata-Version: 2.0
Name: processy
Version: 1.0.7
Summary: A popen wrapper.
Home-page: https://github.com/feluxe/processy
Author: Felix Meyer-Wolters
Author-email: felix@meyerwolters.de
License: unlicensed
Download-URL: https://github.com/feluxe/processy/tarball/1.0.7
Keywords: popen,wraper
Platform: 
